odoo10_addon_mrp_production_putaway_strategy-10.0.1.0.1-py2.7-nspkg.pth
odoo/addons/mrp_production_putaway_strategy/README.rst
odoo/addons/mrp_production_putaway_strategy/__init__.py
odoo/addons/mrp_production_putaway_strategy/__manifest__.py
odoo/addons/mrp_production_putaway_strategy/i18n/de.po
odoo/addons/mrp_production_putaway_strategy/i18n/es.po
odoo/addons/mrp_production_putaway_strategy/i18n/es_MX.po
odoo/addons/mrp_production_putaway_strategy/i18n/fr.po
odoo/addons/mrp_production_putaway_strategy/i18n/gl.po
odoo/addons/mrp_production_putaway_strategy/i18n/hr.po
odoo/addons/mrp_production_putaway_strategy/i18n/it.po
odoo/addons/mrp_production_putaway_strategy/i18n/mrp_production_putaway_strategy.pot
odoo/addons/mrp_production_putaway_strategy/i18n/pt_BR.po
odoo/addons/mrp_production_putaway_strategy/i18n/ro.po
odoo/addons/mrp_production_putaway_strategy/i18n/sl.po
odoo/addons/mrp_production_putaway_strategy/i18n/tr.po
odoo/addons/mrp_production_putaway_strategy/i18n/vi_VN.po
odoo/addons/mrp_production_putaway_strategy/i18n/zh_CN.po
odoo/addons/mrp_production_putaway_strategy/models/__init__.py
odoo/addons/mrp_production_putaway_strategy/models/mrp_production.py
odoo/addons/mrp_production_putaway_strategy/static/description/icon.png
odoo/addons/mrp_production_putaway_strategy/tests/__init__.py
odoo/addons/mrp_production_putaway_strategy/tests/test_mrp_production.py
odoo10_addon_mrp_production_putaway_strategy-10.0.1.0.1.dist-info/METADATA
odoo10_addon_mrp_production_putaway_strategy-10.0.1.0.1.dist-info/RECORD
odoo10_addon_mrp_production_putaway_strategy-10.0.1.0.1.dist-info/WHEEL
odoo10_addon_mrp_production_putaway_strategy-10.0.1.0.1.dist-info/namespace_packages.txt
odoo10_addon_mrp_production_putaway_strategy-10.0.1.0.1.dist-info/top_level.txt
